python_export_file_info/__init__.py
python_export_file_info/main.py
python_export_file_info/utils.py
python_export_file_info-0.0.6.dist-info/LICENSE
python_export_file_info-0.0.6.dist-info/METADATA
python_export_file_info-0.0.6.dist-info/WHEEL
python_export_file_info-0.0.6.dist-info/top_level.txt
python_export_file_info-0.0.6.dist-info/RECORD
