Metadata-Version: 2.1
Name: python-export-file-info
Version: 0.0.6
Summary: CSV File Info List Generator from Folders and Subfolders
Home-page: https://github.com/sannjayy/python_export_file_info
Author: Sanjay Sikdar
Author-email: hello@znas.in
License: MIT
Project-URL: Bug Reports, https://github.com/sannjayy/python_export_file_info/issues
Project-URL: Funding, https://www.paypal.com/paypalme/znasofficial
Project-URL: Say Thanks!, https://saythanks.io/to/sannjayy
Project-URL: Source, https://github.com/sannjayy/python_export_file_info/
Keywords: python,export,file info,csv
Classifier: Development Status :: 5 - Production/Stable
Classifier: Intended Audience :: Developers
Classifier: Topic :: Software Development :: Libraries :: Python Modules
Classifier: Operating System :: OS Independent
Classifier: License :: OSI Approved :: MIT License
Classifier: Programming Language :: Python :: 3.7
Classifier: Programming Language :: Python :: 3.8
Classifier: Programming Language :: Python :: 3.9
Classifier: Programming Language :: Python :: 3.10
Requires-Python: >=3.7, <4
License-File: LICENSE
Requires-Dist: progress (==1.6)
Requires-Dist: py-essentials (==1.4.12)
